kayra/mixup.py
kayra/sparse_image_warp.py
kayra/spec_augment.py
kayra-0.1.dist-info/LICENSE
kayra-0.1.dist-info/METADATA
kayra-0.1.dist-info/WHEEL
kayra-0.1.dist-info/top_level.txt
kayra-0.1.dist-info/RECORD
